[
    {
        "id": "1WpSLQdb9PFjM33cU3dWYs0I_BPmw-buDswuQ0LWi_-Q",
        "name": "Artificial Intelligence and Indian Music Essay",
        "type": "application/vnd.google-apps.document",
        "created_time": "2024-07-02T22:02:39.287Z",
        "modified_time": "2024-07-02T22:02:40.329Z"
    },
    {
        "id": "1ACi1vY78yJ5FglsZQEpX3Vye4mc4khMpdr5b2Z1_E70",
        "name": "Essay on Tabla",
        "type": "application/vnd.google-apps.document",
        "created_time": "2024-07-02T21:54:22.180Z",
        "modified_time": "2024-07-02T21:54:34.019Z"
    },
    {
        "id": "1BYOJ92XrVRUWZxMc6e6UPfPNeOt92M0EM9WGL0hZr-E",
        "name": "AI and Environment Essay",
        "type": "application/vnd.google-apps.document",
        "created_time": "2024-07-02T21:45:47.997Z",
        "modified_time": "2024-07-02T21:45:49.052Z"
    },
    {
        "id": "1P7Z6Plb6-qs5OujWFAGlExmo6L89DlZBPpXrInzO-Zk",
        "name": "Deficient Intelligence and Environment",
        "type": "application/vnd.google-apps.document",
        "created_time": "2024-07-02T21:36:08.027Z",
        "modified_time": "2024-07-02T21:36:15.600Z"
    },
    {
        "id": "1D5XcRsnB0UCACkSak_8vYTIgqeXL3ZpKI3arD11cViQ",
        "name": "Tree Planting and AI Essay",
        "type": "application/vnd.google-apps.document",
        "created_time": "2024-07-02T21:16:40.962Z",
        "modified_time": "2024-07-02T21:16:42.062Z"
    },
    {
        "id": "1LiDKyHd4joYMRZYwoGrMBMbVPAC42CpH1Htqutr1glo",
        "name": "AI in Real Estate and Stock Market",
        "type": "application/vnd.google-apps.document",
        "created_time": "2024-07-02T20:48:15.109Z",
        "modified_time": "2024-07-02T20:48:16.018Z"
    },
    {
        "id": "1xxLarh12sQBTyCwr1LQAWumSs1Y8UwLuCY386pRzqZY",
        "name": "Artificial Intelligence in Stock Trading",
        "type": "application/vnd.google-apps.document",
        "created_time": "2024-07-02T20:25:34.519Z",
        "modified_time": "2024-07-02T20:25:35.619Z"
    },
    {
        "id": "1sSONUh8Cq-mZ8-0u5Y4Mwsd62EJS1529zEsYSAO6aq8",
        "name": "Stock Market Essay",
        "type": "application/vnd.google-apps.document",
        "created_time": "2024-07-02T19:51:37.677Z",
        "modified_time": "2024-07-02T19:51:38.642Z"
    },
    {
        "id": "1uaqFIKuBoInaE2MJWRZL-E5jc13UGONImbRgS-i0FZU",
        "name": "AI and Stock Trading Essay",
        "type": "application/vnd.google-apps.document",
        "created_time": "2024-07-02T14:38:35.055Z",
        "modified_time": "2024-07-02T14:38:36.028Z"
    },
    {
        "id": "1GLr4X_cSU2QHG6VmIUnhAft5-Y6CeLpjajfrxcgDJTM",
        "name": "AI in Real Estate and Stock Market",
        "type": "application/vnd.google-apps.document",
        "created_time": "2024-07-02T14:11:49.691Z",
        "modified_time": "2024-07-02T14:12:19.410Z"
    },
    {
        "id": "1jkE8sTLiAMZ5SGNuPNNe1g5SB7SD5Mpu",
        "name": "Attracting Clients to Real Estate Business",
        "type": "application/vnd.google-apps.folder",
        "created_time": "2024-07-02T11:44:39.953Z",
        "modified_time": "2024-07-02T11:44:39.953Z"
    },
    {
        "id": "1WpSLQdb9PFjM33cU3dWYs0I_BPmw-buDswuQ0LWi_-Q",
        "name": "Artificial Intelligence and Indian Music Essay",
        "type": "application/vnd.google-apps.document",
        "created_time": "2024-07-02T22:02:39.287Z",
        "modified_time": "2024-07-02T22:02:40.329Z"
    },
    {
        "id": "1ACi1vY78yJ5FglsZQEpX3Vye4mc4khMpdr5b2Z1_E70",
        "name": "Essay on Tabla",
        "type": "application/vnd.google-apps.document",
        "created_time": "2024-07-02T21:54:22.180Z",
        "modified_time": "2024-07-02T21:54:34.019Z"
    },
    {
        "id": "1BYOJ92XrVRUWZxMc6e6UPfPNeOt92M0EM9WGL0hZr-E",
        "name": "AI and Environment Essay",
        "type": "application/vnd.google-apps.document",
        "created_time": "2024-07-02T21:45:47.997Z",
        "modified_time": "2024-07-02T21:45:49.052Z"
    },
    {
        "id": "1P7Z6Plb6-qs5OujWFAGlExmo6L89DlZBPpXrInzO-Zk",
        "name": "Deficient Intelligence and Environment",
        "type": "application/vnd.google-apps.document",
        "created_time": "2024-07-02T21:36:08.027Z",
        "modified_time": "2024-07-02T21:36:15.600Z"
    },
    {
        "id": "1D5XcRsnB0UCACkSak_8vYTIgqeXL3ZpKI3arD11cViQ",
        "name": "Tree Planting and AI Essay",
        "type": "application/vnd.google-apps.document",
        "created_time": "2024-07-02T21:16:40.962Z",
        "modified_time": "2024-07-02T21:16:42.062Z"
    },
    {
        "id": "1LiDKyHd4joYMRZYwoGrMBMbVPAC42CpH1Htqutr1glo",
        "name": "AI in Real Estate and Stock Market",
        "type": "application/vnd.google-apps.document",
        "created_time": "2024-07-02T20:48:15.109Z",
        "modified_time": "2024-07-02T20:48:16.018Z"
    },
    {
        "id": "1xxLarh12sQBTyCwr1LQAWumSs1Y8UwLuCY386pRzqZY",
        "name": "Artificial Intelligence in Stock Trading",
        "type": "application/vnd.google-apps.document",
        "created_time": "2024-07-02T20:25:34.519Z",
        "modified_time": "2024-07-02T20:25:35.619Z"
    },
    {
        "id": "1sSONUh8Cq-mZ8-0u5Y4Mwsd62EJS1529zEsYSAO6aq8",
        "name": "Stock Market Essay",
        "type": "application/vnd.google-apps.document",
        "created_time": "2024-07-02T19:51:37.677Z",
        "modified_time": "2024-07-02T19:51:38.642Z"
    },
    {
        "id": "1uaqFIKuBoInaE2MJWRZL-E5jc13UGONImbRgS-i0FZU",
        "name": "AI and Stock Trading Essay",
        "type": "application/vnd.google-apps.document",
        "created_time": "2024-07-02T14:38:35.055Z",
        "modified_time": "2024-07-02T14:38:36.028Z"
    },
    {
        "id": "1GLr4X_cSU2QHG6VmIUnhAft5-Y6CeLpjajfrxcgDJTM",
        "name": "AI in Real Estate and Stock Market",
        "type": "application/vnd.google-apps.document",
        "created_time": "2024-07-02T14:11:49.691Z",
        "modified_time": "2024-07-02T14:12:19.410Z"
    },
    {
        "id": "1jkE8sTLiAMZ5SGNuPNNe1g5SB7SD5Mpu",
        "name": "Attracting Clients to Real Estate Business",
        "type": "application/vnd.google-apps.folder",
        "created_time": "2024-07-02T11:44:39.953Z",
        "modified_time": "2024-07-02T11:44:39.953Z"
    },
    {
        "id": "1WpSLQdb9PFjM33cU3dWYs0I_BPmw-buDswuQ0LWi_-Q",
        "name": "Artificial Intelligence and Indian Music Essay",
        "type": "application/vnd.google-apps.document",
        "created_time": "2024-07-02T22:02:39.287Z",
        "modified_time": "2024-07-02T22:02:40.329Z"
    },
    {
        "id": "1ACi1vY78yJ5FglsZQEpX3Vye4mc4khMpdr5b2Z1_E70",
        "name": "Essay on Tabla",
        "type": "application/vnd.google-apps.document",
        "created_time": "2024-07-02T21:54:22.180Z",
        "modified_time": "2024-07-02T21:54:34.019Z"
    },
    {
        "id": "1BYOJ92XrVRUWZxMc6e6UPfPNeOt92M0EM9WGL0hZr-E",
        "name": "AI and Environment Essay",
        "type": "application/vnd.google-apps.document",
        "created_time": "2024-07-02T21:45:47.997Z",
        "modified_time": "2024-07-02T21:45:49.052Z"
    },
    {
        "id": "1P7Z6Plb6-qs5OujWFAGlExmo6L89DlZBPpXrInzO-Zk",
        "name": "Deficient Intelligence and Environment",
        "type": "application/vnd.google-apps.document",
        "created_time": "2024-07-02T21:36:08.027Z",
        "modified_time": "2024-07-02T21:36:15.600Z"
    },
    {
        "id": "1D5XcRsnB0UCACkSak_8vYTIgqeXL3ZpKI3arD11cViQ",
        "name": "Tree Planting and AI Essay",
        "type": "application/vnd.google-apps.document",
        "created_time": "2024-07-02T21:16:40.962Z",
        "modified_time": "2024-07-02T21:16:42.062Z"
    },
    {
        "id": "1LiDKyHd4joYMRZYwoGrMBMbVPAC42CpH1Htqutr1glo",
        "name": "AI in Real Estate and Stock Market",
        "type": "application/vnd.google-apps.document",
        "created_time": "2024-07-02T20:48:15.109Z",
        "modified_time": "2024-07-02T20:48:16.018Z"
    },
    {
        "id": "1xxLarh12sQBTyCwr1LQAWumSs1Y8UwLuCY386pRzqZY",
        "name": "Artificial Intelligence in Stock Trading",
        "type": "application/vnd.google-apps.document",
        "created_time": "2024-07-02T20:25:34.519Z",
        "modified_time": "2024-07-02T20:25:35.619Z"
    },
    {
        "id": "1sSONUh8Cq-mZ8-0u5Y4Mwsd62EJS1529zEsYSAO6aq8",
        "name": "Stock Market Essay",
        "type": "application/vnd.google-apps.document",
        "created_time": "2024-07-02T19:51:37.677Z",
        "modified_time": "2024-07-02T19:51:38.642Z"
    },
    {
        "id": "1uaqFIKuBoInaE2MJWRZL-E5jc13UGONImbRgS-i0FZU",
        "name": "AI and Stock Trading Essay",
        "type": "application/vnd.google-apps.document",
        "created_time": "2024-07-02T14:38:35.055Z",
        "modified_time": "2024-07-02T14:38:36.028Z"
    },
    {
        "id": "1GLr4X_cSU2QHG6VmIUnhAft5-Y6CeLpjajfrxcgDJTM",
        "name": "AI in Real Estate and Stock Market",
        "type": "application/vnd.google-apps.document",
        "created_time": "2024-07-02T14:11:49.691Z",
        "modified_time": "2024-07-02T14:12:19.410Z"
    },
    {
        "id": "1jkE8sTLiAMZ5SGNuPNNe1g5SB7SD5Mpu",
        "name": "Attracting Clients to Real Estate Business",
        "type": "application/vnd.google-apps.folder",
        "created_time": "2024-07-02T11:44:39.953Z",
        "modified_time": "2024-07-02T11:44:39.953Z"
    },
    {
        "id": "1WpSLQdb9PFjM33cU3dWYs0I_BPmw-buDswuQ0LWi_-Q",
        "name": "Artificial Intelligence and Indian Music Essay",
        "type": "application/vnd.google-apps.document",
        "created_time": "2024-07-02T22:02:39.287Z",
        "modified_time": "2024-07-02T22:02:40.329Z"
    },
    {
        "id": "1ACi1vY78yJ5FglsZQEpX3Vye4mc4khMpdr5b2Z1_E70",
        "name": "Essay on Tabla",
        "type": "application/vnd.google-apps.document",
        "created_time": "2024-07-02T21:54:22.180Z",
        "modified_time": "2024-07-02T21:54:34.019Z"
    },
    {
        "id": "1BYOJ92XrVRUWZxMc6e6UPfPNeOt92M0EM9WGL0hZr-E",
        "name": "AI and Environment Essay",
        "type": "application/vnd.google-apps.document",
        "created_time": "2024-07-02T21:45:47.997Z",
        "modified_time": "2024-07-02T21:45:49.052Z"
    },
    {
        "id": "1P7Z6Plb6-qs5OujWFAGlExmo6L89DlZBPpXrInzO-Zk",
        "name": "Deficient Intelligence and Environment",
        "type": "application/vnd.google-apps.document",
        "created_time": "2024-07-02T21:36:08.027Z",
        "modified_time": "2024-07-02T21:36:15.600Z"
    },
    {
        "id": "1D5XcRsnB0UCACkSak_8vYTIgqeXL3ZpKI3arD11cViQ",
        "name": "Tree Planting and AI Essay",
        "type": "application/vnd.google-apps.document",
        "created_time": "2024-07-02T21:16:40.962Z",
        "modified_time": "2024-07-02T21:16:42.062Z"
    },
    {
        "id": "1LiDKyHd4joYMRZYwoGrMBMbVPAC42CpH1Htqutr1glo",
        "name": "AI in Real Estate and Stock Market",
        "type": "application/vnd.google-apps.document",
        "created_time": "2024-07-02T20:48:15.109Z",
        "modified_time": "2024-07-02T20:48:16.018Z"
    },
    {
        "id": "1xxLarh12sQBTyCwr1LQAWumSs1Y8UwLuCY386pRzqZY",
        "name": "Artificial Intelligence in Stock Trading",
        "type": "application/vnd.google-apps.document",
        "created_time": "2024-07-02T20:25:34.519Z",
        "modified_time": "2024-07-02T20:25:35.619Z"
    },
    {
        "id": "1sSONUh8Cq-mZ8-0u5Y4Mwsd62EJS1529zEsYSAO6aq8",
        "name": "Stock Market Essay",
        "type": "application/vnd.google-apps.document",
        "created_time": "2024-07-02T19:51:37.677Z",
        "modified_time": "2024-07-02T19:51:38.642Z"
    },
    {
        "id": "1uaqFIKuBoInaE2MJWRZL-E5jc13UGONImbRgS-i0FZU",
        "name": "AI and Stock Trading Essay",
        "type": "application/vnd.google-apps.document",
        "created_time": "2024-07-02T14:38:35.055Z",
        "modified_time": "2024-07-02T14:38:36.028Z"
    },
    {
        "id": "1GLr4X_cSU2QHG6VmIUnhAft5-Y6CeLpjajfrxcgDJTM",
        "name": "AI in Real Estate and Stock Market",
        "type": "application/vnd.google-apps.document",
        "created_time": "2024-07-02T14:11:49.691Z",
        "modified_time": "2024-07-02T14:12:19.410Z"
    },
    {
        "id": "1jkE8sTLiAMZ5SGNuPNNe1g5SB7SD5Mpu",
        "name": "Attracting Clients to Real Estate Business",
        "type": "application/vnd.google-apps.folder",
        "created_time": "2024-07-02T11:44:39.953Z",
        "modified_time": "2024-07-02T11:44:39.953Z"
    },
    {
        "id": "1WpSLQdb9PFjM33cU3dWYs0I_BPmw-buDswuQ0LWi_-Q",
        "name": "Artificial Intelligence and Indian Music Essay",
        "type": "application/vnd.google-apps.document",
        "created_time": "2024-07-02T22:02:39.287Z",
        "modified_time": "2024-07-02T22:02:40.329Z"
    },
    {
        "id": "1ACi1vY78yJ5FglsZQEpX3Vye4mc4khMpdr5b2Z1_E70",
        "name": "Essay on Tabla",
        "type": "application/vnd.google-apps.document",
        "created_time": "2024-07-02T21:54:22.180Z",
        "modified_time": "2024-07-02T21:54:34.019Z"
    },
    {
        "id": "1BYOJ92XrVRUWZxMc6e6UPfPNeOt92M0EM9WGL0hZr-E",
        "name": "AI and Environment Essay",
        "type": "application/vnd.google-apps.document",
        "created_time": "2024-07-02T21:45:47.997Z",
        "modified_time": "2024-07-02T21:45:49.052Z"
    },
    {
        "id": "1P7Z6Plb6-qs5OujWFAGlExmo6L89DlZBPpXrInzO-Zk",
        "name": "Deficient Intelligence and Environment",
        "type": "application/vnd.google-apps.document",
        "created_time": "2024-07-02T21:36:08.027Z",
        "modified_time": "2024-07-02T21:36:15.600Z"
    },
    {
        "id": "1D5XcRsnB0UCACkSak_8vYTIgqeXL3ZpKI3arD11cViQ",
        "name": "Tree Planting and AI Essay",
        "type": "application/vnd.google-apps.document",
        "created_time": "2024-07-02T21:16:40.962Z",
        "modified_time": "2024-07-02T21:16:42.062Z"
    },
    {
        "id": "1LiDKyHd4joYMRZYwoGrMBMbVPAC42CpH1Htqutr1glo",
        "name": "AI in Real Estate and Stock Market",
        "type": "application/vnd.google-apps.document",
        "created_time": "2024-07-02T20:48:15.109Z",
        "modified_time": "2024-07-02T20:48:16.018Z"
    },
    {
        "id": "1xxLarh12sQBTyCwr1LQAWumSs1Y8UwLuCY386pRzqZY",
        "name": "Artificial Intelligence in Stock Trading",
        "type": "application/vnd.google-apps.document",
        "created_time": "2024-07-02T20:25:34.519Z",
        "modified_time": "2024-07-02T20:25:35.619Z"
    },
    {
        "id": "1sSONUh8Cq-mZ8-0u5Y4Mwsd62EJS1529zEsYSAO6aq8",
        "name": "Stock Market Essay",
        "type": "application/vnd.google-apps.document",
        "created_time": "2024-07-02T19:51:37.677Z",
        "modified_time": "2024-07-02T19:51:38.642Z"
    },
    {
        "id": "1uaqFIKuBoInaE2MJWRZL-E5jc13UGONImbRgS-i0FZU",
        "name": "AI and Stock Trading Essay",
        "type": "application/vnd.google-apps.document",
        "created_time": "2024-07-02T14:38:35.055Z",
        "modified_time": "2024-07-02T14:38:36.028Z"
    },
    {
        "id": "1GLr4X_cSU2QHG6VmIUnhAft5-Y6CeLpjajfrxcgDJTM",
        "name": "AI in Real Estate and Stock Market",
        "type": "application/vnd.google-apps.document",
        "created_time": "2024-07-02T14:11:49.691Z",
        "modified_time": "2024-07-02T14:12:19.410Z"
    },
    {
        "id": "1jkE8sTLiAMZ5SGNuPNNe1g5SB7SD5Mpu",
        "name": "Attracting Clients to Real Estate Business",
        "type": "application/vnd.google-apps.folder",
        "created_time": "2024-07-02T11:44:39.953Z",
        "modified_time": "2024-07-02T11:44:39.953Z"
    },
    {
        "id": "1WpSLQdb9PFjM33cU3dWYs0I_BPmw-buDswuQ0LWi_-Q",
        "name": "Artificial Intelligence and Indian Music Essay",
        "type": "application/vnd.google-apps.document",
        "created_time": "2024-07-02T22:02:39.287Z",
        "modified_time": "2024-07-02T22:02:40.329Z"
    },
    {
        "id": "1ACi1vY78yJ5FglsZQEpX3Vye4mc4khMpdr5b2Z1_E70",
        "name": "Essay on Tabla",
        "type": "application/vnd.google-apps.document",
        "created_time": "2024-07-02T21:54:22.180Z",
        "modified_time": "2024-07-02T21:54:34.019Z"
    },
    {
        "id": "1BYOJ92XrVRUWZxMc6e6UPfPNeOt92M0EM9WGL0hZr-E",
        "name": "AI and Environment Essay",
        "type": "application/vnd.google-apps.document",
        "created_time": "2024-07-02T21:45:47.997Z",
        "modified_time": "2024-07-02T21:45:49.052Z"
    },
    {
        "id": "1P7Z6Plb6-qs5OujWFAGlExmo6L89DlZBPpXrInzO-Zk",
        "name": "Deficient Intelligence and Environment",
        "type": "application/vnd.google-apps.document",
        "created_time": "2024-07-02T21:36:08.027Z",
        "modified_time": "2024-07-02T21:36:15.600Z"
    },
    {
        "id": "1D5XcRsnB0UCACkSak_8vYTIgqeXL3ZpKI3arD11cViQ",
        "name": "Tree Planting and AI Essay",
        "type": "application/vnd.google-apps.document",
        "created_time": "2024-07-02T21:16:40.962Z",
        "modified_time": "2024-07-02T21:16:42.062Z"
    },
    {
        "id": "1LiDKyHd4joYMRZYwoGrMBMbVPAC42CpH1Htqutr1glo",
        "name": "AI in Real Estate and Stock Market",
        "type": "application/vnd.google-apps.document",
        "created_time": "2024-07-02T20:48:15.109Z",
        "modified_time": "2024-07-02T20:48:16.018Z"
    },
    {
        "id": "1xxLarh12sQBTyCwr1LQAWumSs1Y8UwLuCY386pRzqZY",
        "name": "Artificial Intelligence in Stock Trading",
        "type": "application/vnd.google-apps.document",
        "created_time": "2024-07-02T20:25:34.519Z",
        "modified_time": "2024-07-02T20:25:35.619Z"
    },
    {
        "id": "1sSONUh8Cq-mZ8-0u5Y4Mwsd62EJS1529zEsYSAO6aq8",
        "name": "Stock Market Essay",
        "type": "application/vnd.google-apps.document",
        "created_time": "2024-07-02T19:51:37.677Z",
        "modified_time": "2024-07-02T19:51:38.642Z"
    },
    {
        "id": "1uaqFIKuBoInaE2MJWRZL-E5jc13UGONImbRgS-i0FZU",
        "name": "AI and Stock Trading Essay",
        "type": "application/vnd.google-apps.document",
        "created_time": "2024-07-02T14:38:35.055Z",
        "modified_time": "2024-07-02T14:38:36.028Z"
    },
    {
        "id": "1GLr4X_cSU2QHG6VmIUnhAft5-Y6CeLpjajfrxcgDJTM",
        "name": "AI in Real Estate and Stock Market",
        "type": "application/vnd.google-apps.document",
        "created_time": "2024-07-02T14:11:49.691Z",
        "modified_time": "2024-07-02T14:12:19.410Z"
    },
    {
        "id": "1jkE8sTLiAMZ5SGNuPNNe1g5SB7SD5Mpu",
        "name": "Attracting Clients to Real Estate Business",
        "type": "application/vnd.google-apps.folder",
        "created_time": "2024-07-02T11:44:39.953Z",
        "modified_time": "2024-07-02T11:44:39.953Z"
    },
    {
        "id": "1WpSLQdb9PFjM33cU3dWYs0I_BPmw-buDswuQ0LWi_-Q",
        "name": "Artificial Intelligence and Indian Music Essay",
        "type": "application/vnd.google-apps.document",
        "created_time": "2024-07-02T22:02:39.287Z",
        "modified_time": "2024-07-02T22:02:40.329Z"
    },
    {
        "id": "1ACi1vY78yJ5FglsZQEpX3Vye4mc4khMpdr5b2Z1_E70",
        "name": "Essay on Tabla",
        "type": "application/vnd.google-apps.document",
        "created_time": "2024-07-02T21:54:22.180Z",
        "modified_time": "2024-07-02T21:54:34.019Z"
    },
    {
        "id": "1BYOJ92XrVRUWZxMc6e6UPfPNeOt92M0EM9WGL0hZr-E",
        "name": "AI and Environment Essay",
        "type": "application/vnd.google-apps.document",
        "created_time": "2024-07-02T21:45:47.997Z",
        "modified_time": "2024-07-02T21:45:49.052Z"
    },
    {
        "id": "1P7Z6Plb6-qs5OujWFAGlExmo6L89DlZBPpXrInzO-Zk",
        "name": "Deficient Intelligence and Environment",
        "type": "application/vnd.google-apps.document",
        "created_time": "2024-07-02T21:36:08.027Z",
        "modified_time": "2024-07-02T21:36:15.600Z"
    },
    {
        "id": "1D5XcRsnB0UCACkSak_8vYTIgqeXL3ZpKI3arD11cViQ",
        "name": "Tree Planting and AI Essay",
        "type": "application/vnd.google-apps.document",
        "created_time": "2024-07-02T21:16:40.962Z",
        "modified_time": "2024-07-02T21:16:42.062Z"
    },
    {
        "id": "1LiDKyHd4joYMRZYwoGrMBMbVPAC42CpH1Htqutr1glo",
        "name": "AI in Real Estate and Stock Market",
        "type": "application/vnd.google-apps.document",
        "created_time": "2024-07-02T20:48:15.109Z",
        "modified_time": "2024-07-02T20:48:16.018Z"
    },
    {
        "id": "1xxLarh12sQBTyCwr1LQAWumSs1Y8UwLuCY386pRzqZY",
        "name": "Artificial Intelligence in Stock Trading",
        "type": "application/vnd.google-apps.document",
        "created_time": "2024-07-02T20:25:34.519Z",
        "modified_time": "2024-07-02T20:25:35.619Z"
    },
    {
        "id": "1sSONUh8Cq-mZ8-0u5Y4Mwsd62EJS1529zEsYSAO6aq8",
        "name": "Stock Market Essay",
        "type": "application/vnd.google-apps.document",
        "created_time": "2024-07-02T19:51:37.677Z",
        "modified_time": "2024-07-02T19:51:38.642Z"
    },
    {
        "id": "1uaqFIKuBoInaE2MJWRZL-E5jc13UGONImbRgS-i0FZU",
        "name": "AI and Stock Trading Essay",
        "type": "application/vnd.google-apps.document",
        "created_time": "2024-07-02T14:38:35.055Z",
        "modified_time": "2024-07-02T14:38:36.028Z"
    },
    {
        "id": "1GLr4X_cSU2QHG6VmIUnhAft5-Y6CeLpjajfrxcgDJTM",
        "name": "AI in Real Estate and Stock Market",
        "type": "application/vnd.google-apps.document",
        "created_time": "2024-07-02T14:11:49.691Z",
        "modified_time": "2024-07-02T14:12:19.410Z"
    },
    {
        "id": "1jkE8sTLiAMZ5SGNuPNNe1g5SB7SD5Mpu",
        "name": "Attracting Clients to Real Estate Business",
        "type": "application/vnd.google-apps.folder",
        "created_time": "2024-07-02T11:44:39.953Z",
        "modified_time": "2024-07-02T11:44:39.953Z"
    },
    {
        "id": "1WpSLQdb9PFjM33cU3dWYs0I_BPmw-buDswuQ0LWi_-Q",
        "name": "Artificial Intelligence and Indian Music Essay",
        "type": "application/vnd.google-apps.document",
        "created_time": "2024-07-02T22:02:39.287Z",
        "modified_time": "2024-07-02T22:02:40.329Z"
    },
    {
        "id": "1ACi1vY78yJ5FglsZQEpX3Vye4mc4khMpdr5b2Z1_E70",
        "name": "Essay on Tabla",
        "type": "application/vnd.google-apps.document",
        "created_time": "2024-07-02T21:54:22.180Z",
        "modified_time": "2024-07-02T21:54:34.019Z"
    },
    {
        "id": "1BYOJ92XrVRUWZxMc6e6UPfPNeOt92M0EM9WGL0hZr-E",
        "name": "AI and Environment Essay",
        "type": "application/vnd.google-apps.document",
        "created_time": "2024-07-02T21:45:47.997Z",
        "modified_time": "2024-07-02T21:45:49.052Z"
    },
    {
        "id": "1P7Z6Plb6-qs5OujWFAGlExmo6L89DlZBPpXrInzO-Zk",
        "name": "Deficient Intelligence and Environment",
        "type": "application/vnd.google-apps.document",
        "created_time": "2024-07-02T21:36:08.027Z",
        "modified_time": "2024-07-02T21:36:15.600Z"
    },
    {
        "id": "1D5XcRsnB0UCACkSak_8vYTIgqeXL3ZpKI3arD11cViQ",
        "name": "Tree Planting and AI Essay",
        "type": "application/vnd.google-apps.document",
        "created_time": "2024-07-02T21:16:40.962Z",
        "modified_time": "2024-07-02T21:16:42.062Z"
    },
    {
        "id": "1LiDKyHd4joYMRZYwoGrMBMbVPAC42CpH1Htqutr1glo",
        "name": "AI in Real Estate and Stock Market",
        "type": "application/vnd.google-apps.document",
        "created_time": "2024-07-02T20:48:15.109Z",
        "modified_time": "2024-07-02T20:48:16.018Z"
    },
    {
        "id": "1xxLarh12sQBTyCwr1LQAWumSs1Y8UwLuCY386pRzqZY",
        "name": "Artificial Intelligence in Stock Trading",
        "type": "application/vnd.google-apps.document",
        "created_time": "2024-07-02T20:25:34.519Z",
        "modified_time": "2024-07-02T20:25:35.619Z"
    },
    {
        "id": "1sSONUh8Cq-mZ8-0u5Y4Mwsd62EJS1529zEsYSAO6aq8",
        "name": "Stock Market Essay",
        "type": "application/vnd.google-apps.document",
        "created_time": "2024-07-02T19:51:37.677Z",
        "modified_time": "2024-07-02T19:51:38.642Z"
    },
    {
        "id": "1uaqFIKuBoInaE2MJWRZL-E5jc13UGONImbRgS-i0FZU",
        "name": "AI and Stock Trading Essay",
        "type": "application/vnd.google-apps.document",
        "created_time": "2024-07-02T14:38:35.055Z",
        "modified_time": "2024-07-02T14:38:36.028Z"
    },
    {
        "id": "1GLr4X_cSU2QHG6VmIUnhAft5-Y6CeLpjajfrxcgDJTM",
        "name": "AI in Real Estate and Stock Market",
        "type": "application/vnd.google-apps.document",
        "created_time": "2024-07-02T14:11:49.691Z",
        "modified_time": "2024-07-02T14:12:19.410Z"
    },
    {
        "id": "1jkE8sTLiAMZ5SGNuPNNe1g5SB7SD5Mpu",
        "name": "Attracting Clients to Real Estate Business",
        "type": "application/vnd.google-apps.folder",
        "created_time": "2024-07-02T11:44:39.953Z",
        "modified_time": "2024-07-02T11:44:39.953Z"
    },
    {
        "id": "1WpSLQdb9PFjM33cU3dWYs0I_BPmw-buDswuQ0LWi_-Q",
        "name": "Artificial Intelligence and Indian Music Essay",
        "type": "application/vnd.google-apps.document",
        "created_time": "2024-07-02T22:02:39.287Z",
        "modified_time": "2024-07-02T22:02:40.329Z"
    },
    {
        "id": "1ACi1vY78yJ5FglsZQEpX3Vye4mc4khMpdr5b2Z1_E70",
        "name": "Essay on Tabla",
        "type": "application/vnd.google-apps.document",
        "created_time": "2024-07-02T21:54:22.180Z",
        "modified_time": "2024-07-02T21:54:34.019Z"
    },
    {
        "id": "1BYOJ92XrVRUWZxMc6e6UPfPNeOt92M0EM9WGL0hZr-E",
        "name": "AI and Environment Essay",
        "type": "application/vnd.google-apps.document",
        "created_time": "2024-07-02T21:45:47.997Z",
        "modified_time": "2024-07-02T21:45:49.052Z"
    },
    {
        "id": "1P7Z6Plb6-qs5OujWFAGlExmo6L89DlZBPpXrInzO-Zk",
        "name": "Deficient Intelligence and Environment",
        "type": "application/vnd.google-apps.document",
        "created_time": "2024-07-02T21:36:08.027Z",
        "modified_time": "2024-07-02T21:36:15.600Z"
    },
    {
        "id": "1D5XcRsnB0UCACkSak_8vYTIgqeXL3ZpKI3arD11cViQ",
        "name": "Tree Planting and AI Essay",
        "type": "application/vnd.google-apps.document",
        "created_time": "2024-07-02T21:16:40.962Z",
        "modified_time": "2024-07-02T21:16:42.062Z"
    },
    {
        "id": "1LiDKyHd4joYMRZYwoGrMBMbVPAC42CpH1Htqutr1glo",
        "name": "AI in Real Estate and Stock Market",
        "type": "application/vnd.google-apps.document",
        "created_time": "2024-07-02T20:48:15.109Z",
        "modified_time": "2024-07-02T20:48:16.018Z"
    },
    {
        "id": "1xxLarh12sQBTyCwr1LQAWumSs1Y8UwLuCY386pRzqZY",
        "name": "Artificial Intelligence in Stock Trading",
        "type": "application/vnd.google-apps.document",
        "created_time": "2024-07-02T20:25:34.519Z",
        "modified_time": "2024-07-02T20:25:35.619Z"
    },
    {
        "id": "1sSONUh8Cq-mZ8-0u5Y4Mwsd62EJS1529zEsYSAO6aq8",
        "name": "Stock Market Essay",
        "type": "application/vnd.google-apps.document",
        "created_time": "2024-07-02T19:51:37.677Z",
        "modified_time": "2024-07-02T19:51:38.642Z"
    },
    {
        "id": "1uaqFIKuBoInaE2MJWRZL-E5jc13UGONImbRgS-i0FZU",
        "name": "AI and Stock Trading Essay",
        "type": "application/vnd.google-apps.document",
        "created_time": "2024-07-02T14:38:35.055Z",
        "modified_time": "2024-07-02T14:38:36.028Z"
    },
    {
        "id": "1GLr4X_cSU2QHG6VmIUnhAft5-Y6CeLpjajfrxcgDJTM",
        "name": "AI in Real Estate and Stock Market",
        "type": "application/vnd.google-apps.document",
        "created_time": "2024-07-02T14:11:49.691Z",
        "modified_time": "2024-07-02T14:12:19.410Z"
    },
    {
        "id": "1jkE8sTLiAMZ5SGNuPNNe1g5SB7SD5Mpu",
        "name": "Attracting Clients to Real Estate Business",
        "type": "application/vnd.google-apps.folder",
        "created_time": "2024-07-02T11:44:39.953Z",
        "modified_time": "2024-07-02T11:44:39.953Z"
    },
    {
        "id": "1WpSLQdb9PFjM33cU3dWYs0I_BPmw-buDswuQ0LWi_-Q",
        "name": "Artificial Intelligence and Indian Music Essay",
        "type": "application/vnd.google-apps.document",
        "created_time": "2024-07-02T22:02:39.287Z",
        "modified_time": "2024-07-02T22:02:40.329Z"
    },
    {
        "id": "1ACi1vY78yJ5FglsZQEpX3Vye4mc4khMpdr5b2Z1_E70",
        "name": "Essay on Tabla",
        "type": "application/vnd.google-apps.document",
        "created_time": "2024-07-02T21:54:22.180Z",
        "modified_time": "2024-07-02T21:54:34.019Z"
    },
    {
        "id": "1BYOJ92XrVRUWZxMc6e6UPfPNeOt92M0EM9WGL0hZr-E",
        "name": "AI and Environment Essay",
        "type": "application/vnd.google-apps.document",
        "created_time": "2024-07-02T21:45:47.997Z",
        "modified_time": "2024-07-02T21:45:49.052Z"
    },
    {
        "id": "1P7Z6Plb6-qs5OujWFAGlExmo6L89DlZBPpXrInzO-Zk",
        "name": "Deficient Intelligence and Environment",
        "type": "application/vnd.google-apps.document",
        "created_time": "2024-07-02T21:36:08.027Z",
        "modified_time": "2024-07-02T21:36:15.600Z"
    },
    {
        "id": "1D5XcRsnB0UCACkSak_8vYTIgqeXL3ZpKI3arD11cViQ",
        "name": "Tree Planting and AI Essay",
        "type": "application/vnd.google-apps.document",
        "created_time": "2024-07-02T21:16:40.962Z",
        "modified_time": "2024-07-02T21:16:42.062Z"
    },
    {
        "id": "1LiDKyHd4joYMRZYwoGrMBMbVPAC42CpH1Htqutr1glo",
        "name": "AI in Real Estate and Stock Market",
        "type": "application/vnd.google-apps.document",
        "created_time": "2024-07-02T20:48:15.109Z",
        "modified_time": "2024-07-02T20:48:16.018Z"
    },
    {
        "id": "1xxLarh12sQBTyCwr1LQAWumSs1Y8UwLuCY386pRzqZY",
        "name": "Artificial Intelligence in Stock Trading",
        "type": "application/vnd.google-apps.document",
        "created_time": "2024-07-02T20:25:34.519Z",
        "modified_time": "2024-07-02T20:25:35.619Z"
    },
    {
        "id": "1sSONUh8Cq-mZ8-0u5Y4Mwsd62EJS1529zEsYSAO6aq8",
        "name": "Stock Market Essay",
        "type": "application/vnd.google-apps.document",
        "created_time": "2024-07-02T19:51:37.677Z",
        "modified_time": "2024-07-02T19:51:38.642Z"
    },
    {
        "id": "1uaqFIKuBoInaE2MJWRZL-E5jc13UGONImbRgS-i0FZU",
        "name": "AI and Stock Trading Essay",
        "type": "application/vnd.google-apps.document",
        "created_time": "2024-07-02T14:38:35.055Z",
        "modified_time": "2024-07-02T14:38:36.028Z"
    },
    {
        "id": "1GLr4X_cSU2QHG6VmIUnhAft5-Y6CeLpjajfrxcgDJTM",
        "name": "AI in Real Estate and Stock Market",
        "type": "application/vnd.google-apps.document",
        "created_time": "2024-07-02T14:11:49.691Z",
        "modified_time": "2024-07-02T14:12:19.410Z"
    },
    {
        "id": "1jkE8sTLiAMZ5SGNuPNNe1g5SB7SD5Mpu",
        "name": "Attracting Clients to Real Estate Business",
        "type": "application/vnd.google-apps.folder",
        "created_time": "2024-07-02T11:44:39.953Z",
        "modified_time": "2024-07-02T11:44:39.953Z"
    },
    {
        "id": "1WpSLQdb9PFjM33cU3dWYs0I_BPmw-buDswuQ0LWi_-Q",
        "name": "Artificial Intelligence and Indian Music Essay",
        "type": "application/vnd.google-apps.document",
        "created_time": "2024-07-02T22:02:39.287Z",
        "modified_time": "2024-07-02T22:02:40.329Z"
    },
    {
        "id": "1ACi1vY78yJ5FglsZQEpX3Vye4mc4khMpdr5b2Z1_E70",
        "name": "Essay on Tabla",
        "type": "application/vnd.google-apps.document",
        "created_time": "2024-07-02T21:54:22.180Z",
        "modified_time": "2024-07-02T21:54:34.019Z"
    },
    {
        "id": "1BYOJ92XrVRUWZxMc6e6UPfPNeOt92M0EM9WGL0hZr-E",
        "name": "AI and Environment Essay",
        "type": "application/vnd.google-apps.document",
        "created_time": "2024-07-02T21:45:47.997Z",
        "modified_time": "2024-07-02T21:45:49.052Z"
    },
    {
        "id": "1P7Z6Plb6-qs5OujWFAGlExmo6L89DlZBPpXrInzO-Zk",
        "name": "Deficient Intelligence and Environment",
        "type": "application/vnd.google-apps.document",
        "created_time": "2024-07-02T21:36:08.027Z",
        "modified_time": "2024-07-02T21:36:15.600Z"
    },
    {
        "id": "1D5XcRsnB0UCACkSak_8vYTIgqeXL3ZpKI3arD11cViQ",
        "name": "Tree Planting and AI Essay",
        "type": "application/vnd.google-apps.document",
        "created_time": "2024-07-02T21:16:40.962Z",
        "modified_time": "2024-07-02T21:16:42.062Z"
    },
    {
        "id": "1LiDKyHd4joYMRZYwoGrMBMbVPAC42CpH1Htqutr1glo",
        "name": "AI in Real Estate and Stock Market",
        "type": "application/vnd.google-apps.document",
        "created_time": "2024-07-02T20:48:15.109Z",
        "modified_time": "2024-07-02T20:48:16.018Z"
    },
    {
        "id": "1xxLarh12sQBTyCwr1LQAWumSs1Y8UwLuCY386pRzqZY",
        "name": "Artificial Intelligence in Stock Trading",
        "type": "application/vnd.google-apps.document",
        "created_time": "2024-07-02T20:25:34.519Z",
        "modified_time": "2024-07-02T20:25:35.619Z"
    },
    {
        "id": "1sSONUh8Cq-mZ8-0u5Y4Mwsd62EJS1529zEsYSAO6aq8",
        "name": "Stock Market Essay",
        "type": "application/vnd.google-apps.document",
        "created_time": "2024-07-02T19:51:37.677Z",
        "modified_time": "2024-07-02T19:51:38.642Z"
    },
    {
        "id": "1uaqFIKuBoInaE2MJWRZL-E5jc13UGONImbRgS-i0FZU",
        "name": "AI and Stock Trading Essay",
        "type": "application/vnd.google-apps.document",
        "created_time": "2024-07-02T14:38:35.055Z",
        "modified_time": "2024-07-02T14:38:36.028Z"
    },
    {
        "id": "1GLr4X_cSU2QHG6VmIUnhAft5-Y6CeLpjajfrxcgDJTM",
        "name": "AI in Real Estate and Stock Market",
        "type": "application/vnd.google-apps.document",
        "created_time": "2024-07-02T14:11:49.691Z",
        "modified_time": "2024-07-02T14:12:19.410Z"
    },
    {
        "id": "1jkE8sTLiAMZ5SGNuPNNe1g5SB7SD5Mpu",
        "name": "Attracting Clients to Real Estate Business",
        "type": "application/vnd.google-apps.folder",
        "created_time": "2024-07-02T11:44:39.953Z",
        "modified_time": "2024-07-02T11:44:39.953Z"
    },
    {
        "id": "1WpSLQdb9PFjM33cU3dWYs0I_BPmw-buDswuQ0LWi_-Q",
        "name": "Artificial Intelligence and Indian Music Essay",
        "type": "application/vnd.google-apps.document",
        "created_time": "2024-07-02T22:02:39.287Z",
        "modified_time": "2024-07-02T22:02:40.329Z"
    },
    {
        "id": "1ACi1vY78yJ5FglsZQEpX3Vye4mc4khMpdr5b2Z1_E70",
        "name": "Essay on Tabla",
        "type": "application/vnd.google-apps.document",
        "created_time": "2024-07-02T21:54:22.180Z",
        "modified_time": "2024-07-02T21:54:34.019Z"
    },
    {
        "id": "1BYOJ92XrVRUWZxMc6e6UPfPNeOt92M0EM9WGL0hZr-E",
        "name": "AI and Environment Essay",
        "type": "application/vnd.google-apps.document",
        "created_time": "2024-07-02T21:45:47.997Z",
        "modified_time": "2024-07-02T21:45:49.052Z"
    },
    {
        "id": "1P7Z6Plb6-qs5OujWFAGlExmo6L89DlZBPpXrInzO-Zk",
        "name": "Deficient Intelligence and Environment",
        "type": "application/vnd.google-apps.document",
        "created_time": "2024-07-02T21:36:08.027Z",
        "modified_time": "2024-07-02T21:36:15.600Z"
    },
    {
        "id": "1D5XcRsnB0UCACkSak_8vYTIgqeXL3ZpKI3arD11cViQ",
        "name": "Tree Planting and AI Essay",
        "type": "application/vnd.google-apps.document",
        "created_time": "2024-07-02T21:16:40.962Z",
        "modified_time": "2024-07-02T21:16:42.062Z"
    },
    {
        "id": "1LiDKyHd4joYMRZYwoGrMBMbVPAC42CpH1Htqutr1glo",
        "name": "AI in Real Estate and Stock Market",
        "type": "application/vnd.google-apps.document",
        "created_time": "2024-07-02T20:48:15.109Z",
        "modified_time": "2024-07-02T20:48:16.018Z"
    },
    {
        "id": "1xxLarh12sQBTyCwr1LQAWumSs1Y8UwLuCY386pRzqZY",
        "name": "Artificial Intelligence in Stock Trading",
        "type": "application/vnd.google-apps.document",
        "created_time": "2024-07-02T20:25:34.519Z",
        "modified_time": "2024-07-02T20:25:35.619Z"
    },
    {
        "id": "1sSONUh8Cq-mZ8-0u5Y4Mwsd62EJS1529zEsYSAO6aq8",
        "name": "Stock Market Essay",
        "type": "application/vnd.google-apps.document",
        "created_time": "2024-07-02T19:51:37.677Z",
        "modified_time": "2024-07-02T19:51:38.642Z"
    },
    {
        "id": "1uaqFIKuBoInaE2MJWRZL-E5jc13UGONImbRgS-i0FZU",
        "name": "AI and Stock Trading Essay",
        "type": "application/vnd.google-apps.document",
        "created_time": "2024-07-02T14:38:35.055Z",
        "modified_time": "2024-07-02T14:38:36.028Z"
    },
    {
        "id": "1GLr4X_cSU2QHG6VmIUnhAft5-Y6CeLpjajfrxcgDJTM",
        "name": "AI in Real Estate and Stock Market",
        "type": "application/vnd.google-apps.document",
        "created_time": "2024-07-02T14:11:49.691Z",
        "modified_time": "2024-07-02T14:12:19.410Z"
    },
    {
        "id": "1jkE8sTLiAMZ5SGNuPNNe1g5SB7SD5Mpu",
        "name": "Attracting Clients to Real Estate Business",
        "type": "application/vnd.google-apps.folder",
        "created_time": "2024-07-02T11:44:39.953Z",
        "modified_time": "2024-07-02T11:44:39.953Z"
    }
]